mysqlsb/__init__.py
mysqlsb/builder.py
mysqlsb/configuration.py
mysqlsb/exceptions.py
mysqlsb/statements.py
mysqlsb/utils.py
tests/__init__.py
tests/test_builder.py
tests/test_statements.py
mysql_statement_builder-0.3.0.dist-info/LICENSE
mysql_statement_builder-0.3.0.dist-info/METADATA
mysql_statement_builder-0.3.0.dist-info/WHEEL
mysql_statement_builder-0.3.0.dist-info/top_level.txt
mysql_statement_builder-0.3.0.dist-info/RECORD
