Metadata-Version: 2.1
Name: mysql-statement-builder
Version: 0.3.0
Summary: Simplifies writing MySQL statements in non-ORM environments.
Home-page: https://github.com/johnmartins/mysql-statement-builder
Author: Julian Martinsson Bonde
Author-email: julianm@chalmers.se
License: UNKNOWN
Platform: UNKNOWN
Classifier: Programming Language :: Python :: 3
Classifier: Programming Language :: Python :: 3.11
Classifier: Operating System :: OS Independent
Classifier: License :: OSI Approved :: MIT License
License-File: LICENSE
Provides-Extra: dev
Requires-Dist: pytest (==7.*) ; extra == 'dev'
Requires-Dist: twine (>=4.0) ; extra == 'dev'
